hyperstate/__init__.py
hyperstate/command.py
hyperstate/hyperstate.py
hyperstate/lazy.py
hyperstate/msgpack_torch.py
hyperstate/py.typed
hyperstate/schedule.py
hyperstate/schema/__init__.py
hyperstate/schema/help.py
hyperstate/schema/namedtuple_utils.py
hyperstate/schema/rewrite_rule.py
hyperstate/schema/schema_change.py
hyperstate/schema/schema_checker.py
hyperstate/schema/test_dump_schema.py
hyperstate/schema/test_help.py
hyperstate/schema/test_schema_evolution.py
hyperstate/schema/types.py
hyperstate/schema/versioned.py
hyperstate/serde.py
hyperstate/test_checkpoint.py
hyperstate/test_override.py
hyperstate-0.4.4.dist-info/METADATA
hyperstate-0.4.4.dist-info/WHEEL
hyperstate-0.4.4.dist-info/RECORD
