Metadata-Version: 2.1
Name: hyperstate
Version: 0.4.4
Summary: Library for managing hyperparameters and mutable state of machine learning training systems.
License: MIT
Author: Clemens Winter
Author-email: clemenswinter1@gmail.com
Requires-Python: >=3.7.1,<3.11.0
Classifier: License :: OSI Approved :: Apache Software License
Classifier: License :: OSI Approved :: MIT License
Classifier: Programming Language :: Python :: 3
Classifier: Programming Language :: Python :: 3.8
Classifier: Programming Language :: Python :: 3.9
Classifier: Programming Language :: Python :: 3.10
Classifier: Topic :: Scientific/Engineering :: Artificial Intelligence
Requires-Dist: click (>=8.1,<9.0)
Requires-Dist: dill (>=0.3.4,<0.4.0)
Requires-Dist: docstring-parser (>=0.13,<0.14)
Requires-Dist: msgpack (>=1.0.3,<2.0.0)
Requires-Dist: numpy (>=1.21.4,<2.0.0)
Requires-Dist: python-ron (>=0.2.1,<0.3.0)
Requires-Dist: typing-extensions (>=4.3.0,<5.0.0)
